{
    "dislikes": 9,
    "video": "",
    "publishedOn": "Sun Mar 24 2024 22:10:14 GMT+0530 (India Standard Time)",
    "slug": "target-sum-dp-21",
    "aid": "1716",
    "title": "Target Sum (DP - 21)",
    "tuf_plus": "https://takeuforward.org/plus/dsa/problems/target-sum",
    "topics": [
        {
            "topic-id": "arrays",
            "topic-title": "Arrays"
        },
        {
            "topic-id": "data-structure",
            "topic-title": "Data Structures"
        },
        {
            "topic-id": "dynamic-programming",
            "topic-title": "Dynamic Programming"
        },
        {
            "topic-id": "recursion",
            "topic-title": "Recursion"
        }
    ],
    "content": "<!-- wp:paragraph -->\n<p><strong>Problem Link: </strong><a href=\"https://www.codingninjas.com/codestudio/problems/target-sum_4127362?source=youtube&amp;campaign=striver_dp_videos&amp;utm_source=youtube&amp;utm_medium=affiliate&amp;utm_campaign=striver_dp_videos\" target=\"_blank\" rel=\"noreferrer noopener nofollow\">Target Sum</a></p>\n<!-- /wp:paragraph -->\n\n<!-- wp:paragraph -->\n<p><strong>Problem Description:</strong></p>\n<!-- /wp:paragraph -->\n\n<!-- wp:paragraph -->\n<p>We are given an array \u2018ARR\u2019 of size \u2018N\u2019 and a number \u2018Target\u2019. Our task is to build an expression from the given array where we can place a \u2018+\u2019 or \u2018-\u2019 sign in front of an integer. We want to place a sign in front of every integer of the array and get our required target. We need to count the number of ways in which we can achieve our required target.</p>\n<!-- /wp:paragraph -->\n\n<!-- wp:paragraph -->\n<p></p>\n<!-- /wp:paragraph -->\n\n<!-- wp:html -->\n<!-- This is Examples Drop-Down -->\n<div id=\"article_examples\">\n<details class=\"article_example_details\">\n<summary class=\"article_example_summary\">\n<span><strong>\nExamples\n</strong>\n</span>\n<svg class=\"arrow-svg opacity-75\" xmlns=\"http://www.w3.org/2000/svg\" viewBox=\"0 0 20 20\">\n<path d=\"M12.95 10.707l.707-.707L8 4.343 6.586 5.757 10.828 10l-4.242 4.243L8 15.657l4.95-4.95z\"></path>\n</svg>\n</summary>\n<div class=\"atricle_example_content\">\n<pre class=\"wp-block-preformatted\"><!-- Insert New Examples Here -->\n<pre class=\"wp-block-preformatted\"><strong>Example:</strong>\n\n<img width=\"484\" height=\"394\" src=\"https://lh5.googleusercontent.com/vMo25kPQM_P2t1Uav9EXflTOGwHNajBPXO_GULWMbNbgnuPP7CcxksX_B0szm13u7OKd2JiouZYNoWFEomMibbxBAlt_hi66_-Zd2NtLeL9-9WgjxBFyaCNmh3HUT1orTLr6l_r1\"></pre>\n</pre>\n</div>\n</details>\n</div>\n<!-- /wp:html -->\n\n<!-- wp:html -->\n<!-- This is Practice Section-->\n<div class=\"practice\">\n<span><strong>Practice: </strong></span>\n<div class=\"problem-buttons\">\n\n<!-- Add Problem Link inside href -->\n<a href=\"https://www.codingninjas.com/studio/problems/target-sum_4127362?utm_source=striver&amp;utm_medium=website&amp;utm_campaign=a_zcoursetuf\" target=\"_blank\" rel=\"noopener\">\n<span>Solve Problem</span>\n<img src=\"https://static.takeuforward.org/wp/uploads/2023/04/Group-11-5.png\" alt=\"code-studio\">\n</a>\n</div>\n</div>\n<p class=\"new-disclaimer\"><strong><em>Disclaimer</em></strong>: <em>Don\u2019t jump directly to the solution, try it out\nyourself first. </em></p>\n<!-- /wp:html -->\n\n<!-- wp:html -->\n<div class=\"horizontal_navbar_dsa_article\">\n<div class=\"grid_container_three\">\n<a href=\"#brute-force-approach\" class=\"three-boxes box-a\">\nMemorization approach\n</a>\n<a href=\"#better-approach\" class=\"three-boxes box-b\">\nTabulation approach\n</a>\n<a href=\"#optimal-approach\" class=\"three-boxes box-c\">\nSpace Optimization\n</a>\n<a href=\"#dsa_article_video_explanation\" class=\"three-boxes box-d\">\n<svg width=\"26\" height=\"26\" viewBox=\"0 0 20 14\" fill=\"none\" xmlns=\"http://www.w3.org/2000/svg\">\n<path d=\"M8 10L13.19 7L8 4V10ZM19.56 2.17C19.69 2.64 19.78 3.27 19.84 4.07C19.91 4.87 19.94 5.56 19.94 6.16L20 7C20 9.19 19.84 10.8 19.56 11.83C19.31 12.73 18.73 13.31 17.83 13.56C17.36 13.69 16.5 13.78 15.18 13.84C13.88 13.91 12.69 13.94 11.59 13.94L10 14C5.81 14 3.2 13.84 2.17 13.56C1.27 13.31 0.69 12.73 0.44 11.83C0.31 11.36 0.22 10.73 0.16 9.93C0.0900001 9.13 0.0599999 8.44 0.0599999 7.84L0 7C0 4.81 0.16 3.2 0.44 2.17C0.69 1.27 1.27 0.69 2.17 0.44C2.64 0.31 3.5 0.22 4.82 0.16C6.12 0.0899998 7.31 0.0599999 8.41 0.0599999L10 0C14.19 0 16.8 0.16 17.83 0.44C18.73 0.69 19.31 1.27 19.56 2.17Z\" fill=\"red\"></path>\n</svg>\n\n</a>\n<div class=\"box-e tooltip\">\n<svg viewBox=\"0 0 20 20\" fill=\"none\" xmlns=\"http://www.w3.org/2000/svg\">\n<path d=\"M12.842 9.25L11.9577 10.17C11.2502 10.89 10.8081 11.5 10.8081 13H8.84297V12.5C8.84297 11.39 9.28511 10.39 9.99255 9.67L11.2109 8.41C11.5745 8.05 11.7906 7.55 11.7906 7C11.7906 6.46957 11.5836 5.96086 11.2151 5.58579C10.8465 5.21071 10.3467 5 9.82552 5C9.30434 5 8.80451 5.21071 8.43598 5.58579C8.06745 5.96086 7.86041 6.46957 7.86041 7H5.89531C5.89531 5.93913 6.30938 4.92172 7.04644 4.17157C7.7835 3.42143 8.78316 3 9.82552 3C10.8679 3 11.8675 3.42143 12.6046 4.17157C13.3417 4.92172 13.7557 5.93913 13.7557 7C13.7543 7.84324 13.4259 8.65183 12.842 9.25ZM10.8081 17H8.84297V15H10.8081M9.82552 0C8.53521 0 7.25754 0.258658 6.06545 0.761205C4.87337 1.26375 3.79021 2.00035 2.87783 2.92893C1.03519 4.8043 0 7.34784 0 10C0 12.6522 1.03519 15.1957 2.87783 17.0711C3.79021 17.9997 4.87337 18.7362 6.06545 19.2388C7.25754 19.7413 8.53521 20 9.82552 20C12.4314 20 14.9306 18.9464 16.7732 17.0711C18.6158 15.1957 19.651 12.6522 19.651 10C19.651 4.47 15.2296 0 9.82552 0Z\" fill=\"black\"></path>\n</svg>\n<div class=\"bottom\">\n<p>Expand any one approach by clicking the given options in the bar. Clicking one approach on bar,\ncloses all other expands. You can manually expand more than one approach at a time</p>\n<i></i>\n</div>\n\n</div>\n</div>\n</div>\n<!-- /wp:html -->\n\n<!-- wp:html -->\n<!-- This is Approaches Drop-Down -->\n<div class=\"dsa_article_dropdown_approachs \">\n\n<!-- Brute Force Approach Starts from here -->\n<div id=\"brute-force-approach\">\n<details>\n<summary class=\"main-summary\">\n<span>\nMemorization Approach\n</span>\n<svg class=\"arrow-svg opacity-75\" xmlns=\"http://www.w3.org/2000/svg\" viewBox=\"0 0 20 20\">\n<path d=\"M12.95 10.707l.707-.707L8 4.343 6.586 5.757 10.828 10l-4.242 4.243L8 15.657l4.95-4.95z\">\n</path>\n</svg>\n</summary>\n<div class=\"common-drops\">\n<details class=\"secondary-details\" open=\"\">\n<summary class=\"secondary-summary\">\n<span>\nAlgorithm / Intuition\n</span>\n<svg class=\"arrow-svg opacity-75\" xmlns=\"http://www.w3.org/2000/svg\" viewBox=\"0 0 20 20\">\n<path d=\"M12.95 10.707l.707-.707L8 4.343 6.586 5.757 10.828 10l-4.242 4.243L8 15.657l4.95-4.95z\">\n</path>\n</svg>\n</summary>\n<div class=\"approach-algorithm\">\n\n<!-- Insert Algorithm / Intuition of Brute Force Apporach Here -->\n<p>The first approach that comes to our mind is to generate all subsequences and try both options of placing \u2018-\u2019 and \u2018+\u2019 signs and count the expression if it evaluates the answer.<br>This surely will give us the answer but can we try something familiar to the previous problems we have solved?</p>\n<p>The answer is <strong>yes! </strong>We can use the concept we studied in the following article <a href=\"https://takeuforward.org/data-structure/count-partitions-with-given-difference-dp-18/\" target=\"_blank\" rel=\"noreferrer noopener\">Count Partitions with Given Difference (DP \u2013 18)</a>.</p>\n<p>The following insights will help us to understand intuition better:</p>\n<ul><li>If we think deeper, we can say that the given \u2018target\u2019 can be expressed as addition of two integers (say S1 and S2).&nbsp;</li></ul>\n<p><strong>S1 + S2 = target</strong> &nbsp; \u2013 (i)</p>\n<ul><li>Now, from where will this S1 and S2 come?&nbsp; If we are given the array as <strong>[a,b,c,d,e],</strong> we want to place \u2018+\u2019 or \u2018-\u2019 signs in front of every array element and then add it. One example is :</li></ul>\n<p><strong>+a-b-c+d+e </strong>which can be written as <strong>(+a+d+e) + </strong>(-b-c)<strong>.</strong></p>\n<p>Therefore, we can say that <strong>S1=(+a+d+e) </strong>and <strong>S2=(-b-c)</strong> for this example.</p>\n<ul><li>&nbsp;If we calculate the total sum of elements of the array (say totSum), we can can say that,</li></ul>\n<p><strong>S1 = totSum - S2</strong>&nbsp; &nbsp; &nbsp; \u2013 (ii)</p>\n<ul><li>Now solving for equations (i) and (iii), we can say that&nbsp;</li></ul>\n<p><strong>S2 = (totSum - target)/2 </strong>&nbsp;&nbsp;&nbsp;\u2013 (iv)</p>\n<p>Therefore this question is modified to \u201cCount Number of subsets with sum (totSum - target)/2 \u201d. This is exactly what we had discussed in the article&nbsp; <a href=\"https://takeuforward.org/data-structure/count-subsets-with-sum-k-dp-17/\" target=\"_blank\" rel=\"noreferrer noopener\">Count Subsets with Sum K</a>.</p>\n<p><strong>Edge Cases:</strong></p>\n<p>The following edge cases need to be handled:</p>\n<ul><li>As the array elements are positive integers including zero, we don\u2019t want to find the case when S2 is negative or we can say that totSum is lesser than D, therefore if totSum&lt;target, we simply return 0.</li><li>S2 can\u2019t be a fraction, as all elements are integers, therefore if totSum - target is odd, we can return 0.</li></ul>\n<p>From here on we will discuss the approach to \u201cCount Subsets with Sum K\u201d with the required modifications. Moreover, as the array elements can also contain 0, we will handle it as discussed in part-1 of this article.</p>\n<p><strong>Steps to form the recursive solution:&nbsp;</strong></p>\n<p>We will first form the recursive solution by the three points mentioned in <a href=\"https://takeuforward.org/data-structure/dynamic-programming-introduction/\" target=\"_blank\" rel=\"noreferrer noopener\">Dynamic Programming Introduction</a>.&nbsp;</p>\n<p><strong>Step 1: </strong>Express the problem in terms of indexes.</p>\n<p>The array will have an index but there is one more parameter \u201ctarget\u201d. We are given the initial problem to find whether there exists in the whole array a subsequence whose sum is equal to the target.</p>\n<p>So, we can say that initially, we need to find(n-1, target) which means that we are counting the number of subsequences in the array from index 0 to n-1, whose sum is equal to the target. Similarly, we can generalize it for any index ind as follows:</p>\n<p><img width=\"624\" height=\"77\" src=\"https://lh6.googleusercontent.com/Tg1yIUORXxkIz29VFcvKqlZoIkau7juWUUkmeBzUbR7Ir_ojbRefP-YDS854B1DcB3oxzgtyxJhodK2DjsgNU9H7d0KWJ9CTeOYuzRHdQM3GPt1Jq9ywanbT1qx4oaoB3_I0kDUc\"></p>\n<p><strong>Base Cases:</strong></p>\n<ul><li>If target == 0, it means that we have already found the subsequence from the previous steps, so we can return 1.</li><li>If ind==0, it means we are at the first element, so we need to return arr[ind]==target. If the element is equal to the target we return 1 else we return 0.</li></ul>\n<p><img width=\"396\" height=\"284\" src=\"https://lh6.googleusercontent.com/ZNA56C9DefUxAth8bkBBpGZ2VcYp5MB1jEjz1fkidtgpAeDTZxeQq5jPLU3nfR9Mot7fbmFcVtcAqo__HzA_bHvC_fcyhKSptlyos9zbSSQpASm5WFkZY_MaI-qrcEUqrEvEMNFW\"></p>\n<p><strong>Step 2: </strong>Try out all possible choices at a given index.</p>\n<p>We need to generate all the subsequences. We will use the pick/non-pick technique as discussed in this video \u201c<a href=\"https://www.youtube.com/watch?v=AxNNVECce8c\" target=\"_blank\" rel=\"noreferrer noopener\">Recursion on Subsequences</a>\u201d.</p>\n<p>We have two choices:</p>\n<ul><li><strong>Exclude the current element in the subsequence: </strong>We first try to find a subsequence without considering the current index element. For this, we will make a recursive call to f(ind-1,target).</li><li><strong>Include the current element in the subsequence:</strong> We will try to find a subsequence by considering the current index as element as part of subsequence. As we have included arr[ind], the updated target which we need to find in the rest if the array will be target - arr[ind]. Therefore, we will call f(ind-1,target-arr[ind]).</li></ul>\n<p><strong>Note: </strong>We will consider the current element in the subsequence only when the current element is less than or equal to the target.</p>\n<p><img width=\"422\" height=\"392\" src=\"https://lh5.googleusercontent.com/RZVIi-SEadz4ussGmd7HaRqOOg2e69n6dyhWglLJ5uf3iqK1_dv1rCCRugNOvRXb8wIZGRE2F9OgRoratgWZTB4x9heyVZAamEbG_L68Ufz7XJDeYOCU99BXEjvExoILeN4Yusrj\"></p>\n<p><strong>Step 3:&nbsp; Return sum of taken and notTaken</strong></p>\n<p>As we have to return the total count of subsets with the target sum, we will return the sum of taken and notTaken from our recursive call.</p>\n<p>The final pseudocode after steps 1, 2, and 3:</p>\n<p><img width=\"452\" height=\"459\" src=\"https://lh4.googleusercontent.com/GXHrHVmcA-exoMgbh8Ur-xTaVslPJUD4CgFoAJnqfpFCM1eimvNd08Y8t8n8KWsRbTfssK3wFYBGxwFHQkRd_5ETixOKIHqNIS5kUVwuAfBZxRkBC-TRvk_wCiyXiqrdBVoU4gJ_\"></p>\n<p><strong>Steps to memoize a recursive solution:</strong></p>\n<p>If we draw the recursion tree, we will see that there are overlapping subproblems. In order to convert a recursive solution the following steps will be taken:</p>\n<ol><li>Create a dp array of size [n][k+1]. The size of the input array is \u2018n\u2019, so the index will always lie between \u20180\u2019 and \u2018n-1\u2019. The target can take any value between \u20180\u2019 and \u2018k\u2019. Therefore we take the dp array as dp[n][k+1]</li><li>We initialize the dp array to -1.</li><li>Whenever we want to find the answer of particular parameters (say f(ind,target)), we first check whether the answer is already calculated using the dp array(i.e dp[ind][target]!= -1 ). If yes, simply return the value from the dp array.</li><li>If not, then we are finding the answer for the given value for the first time, we will use the recursive relation as usual but before returning from the function, we will set dp[ind][target] to the solution we get.</li></ol>\n</div>\n</details>\n<details class=\"code-section secondary-details\">\n<summary class=\"secondary-summary\">\n<span>\nCode\n</span>\n<svg class=\"arrow-svg opacity-75\" xmlns=\"http://www.w3.org/2000/svg\" viewBox=\"0 0 20 20\">\n<path d=\"M12.95 10.707l.707-.707L8 4.343 6.586 5.757 10.828 10l-4.242 4.243L8 15.657l4.95-4.95z\">\n</path>\n</svg>\n</summary>\n<div class=\"code-tabs\">\n<button class=\"code-tab dsa_article_code_active\" data-lang=\"cpp\">C++</button>\n<button class=\"code-tab\" data-lang=\"java\">Java</button>\n<button class=\"code-tab\" data-lang=\"python\">Python</button>\n<button class=\"code-tab\" data-lang=\"javascript\">JavaScript</button>\n<svg width=\"17\" class=\"copy-btn\" height=\"20\" viewBox=\"0 0 17 20\" fill=\"none\" xmlns=\"http://www.w3.org/2000/svg\">\n<path d=\"M2 20C1.45 20 0.979002 19.804 0.587002 19.412C0.195002 19.02 -0.000664969 18.5493 1.69779e-06 18V4H2V18H13V20H2ZM6 16C5.45 16 4.979 15.804 4.587 15.412C4.195 15.02 3.99934 14.5493 4 14V2C4 1.45 4.196 0.979002 4.588 0.587002C4.98 0.195002 5.45067 -0.000664969 6 1.69779e-06H15C15.55 1.69779e-06 16.021 0.196002 16.413 0.588002C16.805 0.980002 17.0007 1.45067 17 2V14C17 14.55 16.804 15.021 16.412 15.413C16.02 15.805 15.5493 16.0007 15 16H6ZM6 14H15V2H6V14Z\">\n</path>\n</svg>\n</div>\n<div class=\"code-content\">\n<div class=\"code-block dsa_article_code_active\" data-lang=\"cpp\">\n<pre class=\"wp-block-code\"><code lang=\"cpp\" class=\"language-cpp\">\n#include &lt;bits/stdc++.h&gt;\nusing namespace std;\n\n// Function to count partitions of the array into subsets with a given target sum\nint countPartitionsUtil(int ind, int target, vector&lt;int&gt;&amp; arr, vector&lt;vector&lt;int&gt;&gt;&amp; dp) {\n    // Base cases\n    if (ind == 0) {\n        if (target == 0 &amp;&amp; arr[0] == 0)\n            return 2; // Two ways to partition: include or exclude the element\n        if (target == 0 || target == arr[0])\n            return 1; // One way to partition: include or exclude the element\n        return 0; // No way to partition\n    }\n    \n    // If the result for this index and target sum is already calculated, return it\n    if (dp[ind][target] != -1)\n        return dp[ind][target];\n        \n    // Calculate the number of ways without taking the current element\n    int notTaken = countPartitionsUtil(ind - 1, target, arr, dp);\n    \n    // Calculate the number of ways by taking the current element\n    int taken = 0;\n    if (arr[ind] &lt;= target)\n        taken = countPartitionsUtil(ind - 1, target - arr[ind], arr, dp);\n        \n    // Store the sum of ways in the DP array and return it\n    return dp[ind][target] = (notTaken + taken);\n}\n\n// Function to count the number of ways to achieve the target sum\nint targetSum(int n, int target, vector&lt;int&gt;&amp; arr) {\n    int totSum = 0;\n    for (int i = 0; i &lt; arr.size(); i++) {\n        totSum += arr[i];\n    }\n    \n    // Checking for edge cases\n    if (totSum - target &lt; 0)\n        return 0; // Not possible to achieve the target sum\n    if ((totSum - target) % 2 == 1)\n        return 0; // The difference between the total sum and target sum must be even\n    \n    int s2 = (totSum - target) / 2; // Calculate the required sum for each subset\n    \n    vector&lt;vector&lt;int&gt;&gt; dp(n, vector&lt;int&gt;(s2 + 1, -1)); // Initialize DP table\n    return countPartitionsUtil(n - 1, s2, arr, dp); // Call the helper function\n}\n\nint main() {\n    vector&lt;int&gt; arr = {1, 2, 3, 1};\n    int target = 3;\n                     \n    int n = arr.size();\n    cout &lt;&lt; \"The number of ways found is \" &lt;&lt; targetSum(n, target, arr) &lt;&lt; endl;\n    \n    return 0; // Return 0 to indicate successful program execution\n}\n</code>\n</pre>\n</div>\n<div class=\"code-block \" data-lang=\"java\">\n<pre class=\"wp-block-code\"><code lang=\"java\" class=\"language-java\">\nimport java.util.*;\n\nclass TUF {\n    // Function to count partitions using dynamic programming\n    static int countPartitionsUtil(int ind, int target, int[] arr, int[][] dp) {\n        // Base case: If we have reached the first element\n        if (ind == 0) {\n            // Check if the target is 0 and the first element is also 0\n            if (target == 0 &amp;&amp; arr[0] == 0)\n                return 2;\n            // Check if the target is equal to the first element or 0\n            if (target == 0 || target == arr[0])\n                return 1;\n            return 0;\n        }\n\n        // If the result for this subproblem has already been calculated, return it\n        if (dp[ind][target] != -1)\n            return dp[ind][target];\n\n        // Calculate the number of ways without taking the current element\n        int notTaken = countPartitionsUtil(ind - 1, target, arr, dp);\n\n        // Initialize the number of ways taking the current element as 0\n        int taken = 0;\n\n        // If the current element is less than or equal to the target, calculate 'taken'\n        if (arr[ind] &lt;= target)\n            taken = countPartitionsUtil(ind - 1, target - arr[ind], arr, dp);\n\n        // Store the result in the dp array and return it\n        return dp[ind][target] = (notTaken + taken);\n    }\n\n    // Function to find the number of ways to achieve the target sum\n    static int targetSum(int n, int target, int[] arr) {\n        int totSum = 0;\n\n        // Calculate the total sum of elements in the array\n        for (int i = 0; i &lt; arr.length; i++) {\n            totSum += arr[i];\n        }\n\n        // Checking for edge cases\n        if (totSum - target &lt; 0)\n            return 0;\n        if ((totSum - target) % 2 == 1)\n            return 0;\n\n        // Calculate the second sum based on the total sum and the target\n        int s2 = (totSum - target) / 2;\n\n        // Create a 2D array to store results of subproblems\n        int dp[][] = new int[n][s2 + 1];\n\n        // Initialize the dp array with -1 to indicate that subproblems are not solved yet\n        for (int row[] : dp)\n            Arrays.fill(row, -1);\n\n        // Call the countPartitionsUtil function to calculate the number of ways\n        return countPartitionsUtil(n - 1, s2, arr, dp);\n    }\n\n    public static void main(String args[]) {\n        int arr[] = { 1, 2, 3, 1 };\n        int target = 3;\n\n        int n = arr.length;\n\n        // Call the targetSum function and print the result\n        System.out.println(\"The number of ways found is \" + targetSum(n, target, arr));\n    }\n}\n</code>\n</pre>\n</div>\n<div class=\"code-block\" data-lang=\"python\">\n<pre class=\"wp-block-code\"><code lang=\"python\" class=\"language-python\">\ndef countPartitionsUtil(ind, target, arr, dp):\n    # Base case: If we have reached the first element in the array.\n    if ind == 0:\n        # Check if the target is zero and the first element is also zero, in which case there are two possibilities.\n        if target == 0 and arr[0] == 0:\n            return 2\n        # If the target is equal to the first element, there is one possibility.\n        if target == 0 or target == arr[0]:\n            return 1\n        # Otherwise, there is no valid partition.\n        return 0\n\n    # If the result for this state is already calculated, return it.\n    if dp[ind][target] != -1:\n        return dp[ind][target]\n\n    # Calculate the number of possibilities when the current element is not taken.\n    notTaken = countPartitionsUtil(ind - 1, target, arr, dp)\n    \n    # Initialize a variable for the number of possibilities when the current element is taken.\n    taken = 0\n    if arr[ind] &lt;= target:\n        taken = countPartitionsUtil(ind - 1, target - arr[ind], arr, dp)\n\n    # Store the total number of possibilities in the DP table.\n    dp[ind][target] = notTaken + taken\n    return dp[ind][target]\n\ndef targetSum(n, target, arr):\n    totSum = 0\n    for i in range(len(arr)):\n        totSum += arr[i]\n\n    # Checking for edge cases\n    if totSum - target &lt; 0:\n        return 0\n    if (totSum - target) % 2 == 1:\n        return 0\n\n    s2 = (totSum - target) // 2\n\n    dp = [[-1 for j in range(s2 + 1)] for i in range(n)]\n    return countPartitionsUtil(n - 1, s2, arr, dp)\n\ndef main():\n    arr = [1, 2, 3, 1]\n    target = 3\n    n = len(arr)\n    print(\"The number of ways found is\", targetSum(n, target, arr))\n\nif __name__ == '__main__':\n    main()\n</code>\n</pre>\n</div>\n<div class=\"code-block\" data-lang=\"javascript\">\n<pre class=\"wp-block-code\"><code lang=\"javascript\" class=\"language-javascript\">\nfunction countPartitionsUtil(ind, target, arr, dp) {\n    // Base cases\n    if (ind === 0) {\n        if (target === 0 &amp;&amp; arr[0] === 0)\n            return 2;\n        if (target === 0 || target === arr[0])\n            return 1;\n        return 0;\n    }\n\n    // If the result for this combination of 'ind' and 'target' has already been calculated, return it\n    if (dp[ind][target] !== -1)\n        return dp[ind][target];\n\n    // Recursive cases\n    const notTaken = countPartitionsUtil(ind - 1, target, arr, dp);\n\n    let taken = 0;\n    if (arr[ind] &lt;= target)\n        taken = countPartitionsUtil(ind - 1, target - arr[ind], arr, dp);\n\n    // Store and return the result\n    return dp[ind][target] = notTaken + taken;\n}\n\n// Define a function to find the number of ways to reach the 'target' sum\nfunction targetSum(n, target, arr) {\n    // Calculate the total sum of the array elements\n    let totSum = 0;\n    for (let i = 0; i &lt; arr.length; i++) {\n        totSum += arr[i];\n    }\n\n    // Checking for edge cases\n    if (totSum - target &lt; 0) return 0;\n    if ((totSum - target) % 2 === 1) return 0;\n\n    // Calculate the second subset sum\n    let s2 = (totSum - target) / 2;\n\n    // Create a 2D array to store dynamic programming results, initialized with -1\n    const dp = Array.from({ length: n }, () =&gt; Array(s2 + 1).fill(-1));\n    \n    // Call the countPartitionsUtil function to calculate the result\n    return countPartitionsUtil(n - 1, s2, arr, dp);\n}\n\n// Main function\nfunction main() {\n    const arr = [1, 2, 3, 1];\n    const target = 3;\n    const n = arr.length;\n\n    // Call the targetSum function and print the result\n    console.log(\"The number of ways found is \" + targetSum(n, target, arr));\n}\n\n// Call the main function to start the program\nmain();\n</code>\n</pre>\n</div>\n<p>\n<!-- Insert Output of Brute Force Here -->\n</p><p><strong>Output:</strong> The number of ways found is 2\n\n\n</p>\n<p></p>\n</div>\n</details>\n<details class=\"secondary-details\">\n<summary class=\"secondary-summary\">\n<span>\nComplexity Analysis\n</span>\n<svg class=\"arrow-svg opacity-75\" xmlns=\"http://www.w3.org/2000/svg\" viewBox=\"0 0 20 20\">\n<path d=\"M12.95 10.707l.707-.707L8 4.343 6.586 5.757 10.828 10l-4.242 4.243L8 15.657l4.95-4.95z\">\n</path>\n</svg>\n</summary>\n<p>\n<!-- Insert Time and Space Complexity of Brute Force Here -->\n</p><p><strong>Time Complexity: O(N*K)</strong></p>\n<p>Reason: There are N*K states therefore at max \u2018N*K\u2019 new problems will be solved.</p>\n<p><strong>Space Complexity: O(N*K) + O(N)</strong></p>\n<p>Reason: We are using a recursion stack space(O(N)) and a 2D array ( O(N*K)).</p>\n<p></p>\n</details>\n</div>\n</details>\n</div>\n<!-- Brute Force Approach Ends here -->\n\n\n<!-- Better Approach Starts from here -->\n\n<div id=\"better-approach\">\n<details>\n<summary class=\"main-summary\">\n<span>\nTabulation Approach\n</span>\n<svg class=\"arrow-svg opacity-75\" xmlns=\"http://www.w3.org/2000/svg\" viewBox=\"0 0 20 20\">\n<path d=\"M12.95 10.707l.707-.707L8 4.343 6.586 5.757 10.828 10l-4.242 4.243L8 15.657l4.95-4.95z\">\n</path>\n</svg>\n</summary>\n<div class=\"common-drops\">\n<details class=\"secondary-details\" open=\"\">\n<summary class=\"secondary-summary\">\n<span>\nAlgorithm / Intuition\n</span>\n<svg class=\"arrow-svg opacity-75\" xmlns=\"http://www.w3.org/2000/svg\" viewBox=\"0 0 20 20\">\n<path d=\"M12.95 10.707l.707-.707L8 4.343 6.586 5.757 10.828 10l-4.242 4.243L8 15.657l4.95-4.95z\">\n</path>\n</svg>\n</summary>\n<div class=\"approach-algorithm\">\n\n<!-- Insert Algorithm / Intuition For Better Approach Here -->\n<p>To convert the memoization approach to a tabulation one, create a dp array with the same size as done in memoization. We can initialize it as 0.</p>\n<p><img width=\"624\" height=\"351\" src=\"https://lh4.googleusercontent.com/a-8QeZ3C6K-snL6ExUvvvs4ALfLsaN3crsY-_0w0YbpjydqOjOHbYB6NLpHgdk4GZltov9GIBCOquYPDrrdRk6s9MLpPfTqH9YYQ4RvwOJ0LsWJcDIzacRYUaad4o-YTXzfX3MEj\"></p>\n<p>First, we need to initialize the base conditions of the recursive solution.</p>\n<ul><li>If target == 0, ind can take any value from 0 to n-1, therefore we need to set the value of the first column as 1. </li></ul>\n<p><img width=\"624\" height=\"351\" src=\"https://lh6.googleusercontent.com/vrqd1FDtgwAgs9WLnVaqMsCG97vjCOAXwV_RXNO7ExBRpo_22iXcTC1gpkdjyN74FWCFy67-RGSGNh6ug3IF-6lBisE9fG03cRwyMbL3x2WcorzLSkSz7l5U99wDRnFRwF5UAcz7\"></p>\n<ul><li>The first row dp[0][] indicates that only the first element of the array is considered, therefore for the target value equal to arr[0], only cell with that target will be true, so explicitly set dp[0][arr[0]] =1, (dp[0][arr[0]] means that we are considering the first element of the array with the target equal to the first element itself). Please note that it can happen that arr[0]&gt;target, so we first check it: if(arr[0]&lt;=target) then set dp[0][arr[0]] = 1. </li></ul>\n<p><img width=\"624\" height=\"351\" src=\"https://lh3.googleusercontent.com/iE3ky01aG5lDqCKJLCv54vbhiy5j4YNE5kR6xt7wcZAnsYvAN3nk13GVnV9-J41JSOFZnN6Cx6OPqS-vz6BpEtDn0qFIA_a3m38eZCGEtr8S_4S8GJtadnNDByRlynC6j6A0cibZ\"></p>\n<ul><li>After that, we will set our nested for loops to traverse the dp array, and following the logic discussed in the recursive approach, we will set the value of each cell. Instead of recursive calls, we will use the dp array itself.</li><li>At last, we will return dp[n-1][k] as our answer.</li></ul>\n</div>\n</details>\n<details class=\"code-section secondary-details\">\n<summary class=\"secondary-summary\">\n<span>\nCode\n</span>\n<svg class=\"arrow-svg opacity-75\" xmlns=\"http://www.w3.org/2000/svg\" viewBox=\"0 0 20 20\">\n<path d=\"M12.95 10.707l.707-.707L8 4.343 6.586 5.757 10.828 10l-4.242 4.243L8 15.657l4.95-4.95z\">\n</path>\n</svg>\n</summary>\n<div class=\"code-tabs\">\n<button class=\"code-tab dsa_article_code_active\" data-lang=\"cpp\">C++</button>\n<button class=\"code-tab\" data-lang=\"java\">Java</button>\n<button class=\"code-tab\" data-lang=\"python\">Python</button>\n<button class=\"code-tab\" data-lang=\"javascript\">JavaScript</button>\n<svg width=\"17\" class=\"copy-btn\" height=\"20\" viewBox=\"0 0 17 20\" fill=\"none\" xmlns=\"http://www.w3.org/2000/svg\">\n<path d=\"M2 20C1.45 20 0.979002 19.804 0.587002 19.412C0.195002 19.02 -0.000664969 18.5493 1.69779e-06 18V4H2V18H13V20H2ZM6 16C5.45 16 4.979 15.804 4.587 15.412C4.195 15.02 3.99934 14.5493 4 14V2C4 1.45 4.196 0.979002 4.588 0.587002C4.98 0.195002 5.45067 -0.000664969 6 1.69779e-06H15C15.55 1.69779e-06 16.021 0.196002 16.413 0.588002C16.805 0.980002 17.0007 1.45067 17 2V14C17 14.55 16.804 15.021 16.412 15.413C16.02 15.805 15.5493 16.0007 15 16H6ZM6 14H15V2H6V14Z\">\n</path>\n</svg>\n</div>\n<div class=\"code-content\">\n<div class=\"code-block dsa_article_code_active\" data-lang=\"cpp\">\n<pre class=\"wp-block-code\"><code lang=\"cpp\" class=\"language-cpp\">\n#include &lt;bits/stdc++.h&gt;\nusing namespace std;\n\nconst int mod = (int)1e9 + 7;\n\n// Function to count the number of ways to achieve the target sum\nint findWays(vector&lt;int&gt; &amp;num, int tar) {\n    int n = num.size();\n\n    vector&lt;vector&lt;int&gt;&gt; dp(n, vector&lt;int&gt;(tar + 1, 0));\n\n    if (num[0] == 0)\n        dp[0][0] = 2;  // 2 cases - pick and not pick\n    else\n        dp[0][0] = 1;  // 1 case - not pick\n\n    if (num[0] != 0 &amp;&amp; num[0] &lt;= tar)\n        dp[0][num[0]] = 1;  // 1 case - pick\n\n    for (int ind = 1; ind &lt; n; ind++) {\n        for (int target = 0; target &lt;= tar; target++) {\n\n            int notTaken = dp[ind - 1][target];\n\n            int taken = 0;\n            if (num[ind] &lt;= target)\n                taken = dp[ind - 1][target - num[ind]];\n\n            dp[ind][target] = (notTaken + taken) % mod;\n        }\n    }\n    return dp[n - 1][tar];\n}\n\n// Function to calculate the number of ways to achieve the target sum\nint targetSum(int n, int target, vector&lt;int&gt;&amp; arr) {\n    int totSum = 0;\n    for (int i = 0; i &lt; n; i++) {\n        totSum += arr[i];\n    }\n\n    // Checking for edge cases\n    if (totSum - target &lt; 0 || (totSum - target) % 2 != 0)\n        return 0;  // Not possible to achieve the target sum\n\n    return findWays(arr, (totSum - target) / 2);\n}\n\nint main() {\n    vector&lt;int&gt; arr = {1, 2, 3, 1};\n    int target = 3;\n\n    int n = arr.size();\n    cout &lt;&lt; \"The number of ways found is \" &lt;&lt; targetSum(n, target, arr) &lt;&lt; endl;\n\n    return 0;  // Return 0 to indicate successful program execution\n}\n</code>\n</pre>\n</div>\n<div class=\"code-block \" data-lang=\"java\">\n<pre class=\"wp-block-code\"><code lang=\"java\" class=\"language-java\">\nimport java.util.*;\n\nclass TUF {\n    static int mod = (int) (Math.pow(10, 9) + 7);\n\n    // Function to find the number of ways to achieve the target sum\n    static int findWays(int[] num, int tar) {\n        int n = num.length;\n\n        // Create a 2D array to store results of subproblems\n        int[][] dp = new int[n][tar + 1];\n\n        // Initialize the dp array for the first element of the array\n        if (num[0] == 0)\n            dp[0][0] = 2; // 2 cases - pick and not pick\n        else\n            dp[0][0] = 1; // 1 case - not pick\n\n        if (num[0] != 0 &amp;&amp; num[0] &lt;= tar)\n            dp[0][num[0]] = 1; // 1 case - pick\n\n        // Fill the dp array using dynamic programming\n        for (int ind = 1; ind &lt; n; ind++) {\n            for (int target = 0; target &lt;= tar; target++) {\n                int notTaken = dp[ind - 1][target];\n\n                int taken = 0;\n                if (num[ind] &lt;= target)\n                    taken = dp[ind - 1][target - num[ind]];\n\n                dp[ind][target] = (notTaken + taken) % mod;\n            }\n        }\n\n        return dp[n - 1][tar];\n    }\n\n    // Function to calculate the number of ways to achieve the target sum\n    static int targetSum(int n, int target, int[] arr) {\n        int totSum = 0;\n\n        // Calculate the total sum of elements in the array\n        for (int i = 0; i &lt; n; i++) {\n            totSum += arr[i];\n        }\n\n        // Checking for edge cases\n        if (totSum - target &lt; 0 || (totSum - target) % 2 == 1)\n            return 0;\n\n        return findWays(arr, (totSum - target) / 2);\n    }\n\n    public static void main(String args[]) {\n        int arr[] = { 1, 2, 3, 1 };\n        int target = 3;\n\n        int n = arr.length;\n\n        // Call the targetSum function and print the result\n        System.out.println(\"The number of ways found is \" + targetSum(n, target, arr));\n    }\n}\n</code>\n</pre>\n</div>\n<div class=\"code-block\" data-lang=\"python\">\n<pre class=\"wp-block-code\"><code lang=\"python\" class=\"language-python\">\nmod = int(1e9 + 7)\n\ndef findWays(num, tar):\n    n = len(num)\n    dp = [[0 for i in range(tar + 1)] for j in range(n)]\n\n    if num[0] == 0:\n        dp[0][0] = 2  # 2 cases - pick and not pick\n    else:\n        dp[0][0] = 1  # 1 case - not pick\n\n    if num[0] != 0 and num[0] &lt;= tar:\n        dp[0][num[0]] = 1  # 1 case - pick\n\n    for ind in range(1, n):\n        for target in range(tar + 1):\n            notTaken = dp[ind - 1][target]\n\n            taken = 0\n            if num[ind] &lt;= target:\n                taken = dp[ind - 1][target - num[ind]]\n\n            dp[ind][target] = (notTaken + taken) % mod\n\n    return dp[n - 1][tar]\n\ndef targetSum(n, target, arr):\n    totSum = 0\n    for i in range(n):\n        totSum += arr[i]\n\n    # Checking for edge cases\n    if (totSum - target) &lt; 0 or ((totSum - target) % 2):\n        return 0\n\n    return findWays(arr, (totSum - target) // 2)\n\ndef main():\n    arr = [1, 2, 3, 1]\n    target = 3\n    n = len(arr)\n\n    print(\"The number of ways found is\", targetSum(n, target, arr))\n\nif __name__ == \"__main__\":\n    main()\n</code>\n</pre>\n</div>\n<div class=\"code-block\" data-lang=\"javascript\">\n<pre class=\"wp-block-code\"><code lang=\"javascript\" class=\"language-javascript\">\nconst mod = 1e9 + 7;\n\n// Define a function to find the number of ways to achieve the 'tar' target sum\nfunction findWays(num, tar) {\n    const n = num.length;\n\n    // Create a 2D array 'dp' to store dynamic programming results, initialized with 0\n    const dp = Array.from({ length: n }, () =&gt; Array(tar + 1).fill(0));\n\n    if (num[0] === 0) dp[0][0] = 2;  // 2 cases - pick and not pick\n    else dp[0][0] = 1;  // 1 case - not pick\n\n    if (num[0] !== 0 &amp;&amp; num[0] &lt;= tar) dp[0][num[0]] = 1;  // 1 case - pick\n\n    for (let ind = 1; ind &lt; n; ind++) {\n        for (let target = 0; target &lt;= tar; target++) {\n\n            const notTaken = dp[ind - 1][target];\n\n            let taken = 0;\n            if (num[ind] &lt;= target)\n                taken = dp[ind - 1][target - num[ind]];\n\n            dp[ind][target] = (notTaken + taken) % mod;\n        }\n    }\n\n    return dp[n - 1][tar];\n}\n\n// Define a function to find the number of ways to achieve the 'target' sum using elements from 'arr'\nfunction targetSum(n, target, arr) {\n    let totSum = 0;\n    for (let i = 0; i &lt; n; i++) {\n        totSum += arr[i];\n    }\n\n    // Checking for edge cases\n    if (totSum - target &lt; 0 || (totSum - target) % 2 !== 0) return 0;\n\n    // Calculate the second subset sum\n    const s2 = (totSum - target) / 2;\n\n    // Call the findWays function to calculate the result\n    return findWays(arr, s2);\n}\n\n// Main function\nfunction main() {\n    const arr = [1, 2, 3, 1];\n    const target = 3;\n    const n = arr.length;\n\n    // Call the targetSum function and print the result\n    console.log(\"The number of ways found is \" + targetSum(n, target, arr));\n}\n\n// Call the main function to start the program\nmain();\n</code>\n</pre>\n</div>\n<p>\n<!-- Insert Output of Better Approach Here -->\n<strong>Output:</strong> The number of ways found is 2\n\n</p>\n</div>\n</details>\n<details class=\"secondary-details\">\n<summary class=\"secondary-summary\">\n<span>\nComplexity Analysis\n</span>\n<svg class=\"arrow-svg opacity-75\" xmlns=\"http://www.w3.org/2000/svg\" viewBox=\"0 0 20 20\">\n<path d=\"M12.95 10.707l.707-.707L8 4.343 6.586 5.757 10.828 10l-4.242 4.243L8 15.657l4.95-4.95z\">\n</path>\n</svg>\n</summary>\n<p>\n\n<!-- Insert Time and Space Complexity of Better Approach Here -->\n</p><p><strong>Time Complexity: O(N*K)</strong></p>\n<p>Reason: There are two nested loops</p>\n<p><strong>Space Complexity: O(N*K)</strong></p>\n<p>Reason: We are using an external array of size \u2018N*K\u2019. Stack Space is eliminated.</p>\n<p></p>\n</details>\n</div>\n</details>\n</div>\n<!-- Better Approach Ends from here -->\n\n\n<!-- Optimal Approach Starts from here -->\n\n<div id=\"optimal-approach\">\n<details>\n<summary class=\"main-summary\">\n<span>\nSpace Optimization Approach \n</span>\n<svg class=\"arrow-svg opacity-75\" xmlns=\"http://www.w3.org/2000/svg\" viewBox=\"0 0 20 20\">\n<path d=\"M12.95 10.707l.707-.707L8 4.343 6.586 5.757 10.828 10l-4.242 4.243L8 15.657l4.95-4.95z\">\n</path>\n</svg>\n</summary>\n<div class=\"common-drops\">\n<details class=\"secondary-details\" open=\"\">\n<summary class=\"secondary-summary\">\n<span>\nAlgorithm / Intuition\n</span>\n<svg class=\"arrow-svg opacity-75\" xmlns=\"http://www.w3.org/2000/svg\" viewBox=\"0 0 20 20\">\n<path d=\"M12.95 10.707l.707-.707L8 4.343 6.586 5.757 10.828 10l-4.242 4.243L8 15.657l4.95-4.95z\">\n</path>\n</svg>\n</summary>\n<div class=\"approach-algorithm\">\n\n<!-- Insert Algorithm of Better Approach Here -->\n<p>If we closely look the relation,</p>\n<p><strong>dp[ind][target] =&nbsp; dp[ind-1][target] + dp[ind-1][target-arr[ind]]</strong></p>\n<p>We see that to calculate a value of a cell of the dp array, we need only the previous row values (say prev). So, we don\u2019t need to store an entire array. Hence we can space optimize it.</p>\n<p><strong>Note: </strong>Whenever we create a new row ( say cur), we need to explicitly set its first element as true according to our base condition.</p>\n</div>\n</details>\n<details class=\"code-section secondary-details\">\n<summary class=\"secondary-summary\">\n<span>\nCode\n</span>\n<svg class=\"arrow-svg opacity-75\" xmlns=\"http://www.w3.org/2000/svg\" viewBox=\"0 0 20 20\">\n<path d=\"M12.95 10.707l.707-.707L8 4.343 6.586 5.757 10.828 10l-4.242 4.243L8 15.657l4.95-4.95z\">\n</path>\n</svg>\n</summary>\n<div class=\"code-tabs\">\n<button class=\"code-tab dsa_article_code_active\" data-lang=\"cpp\">C++</button>\n<button class=\"code-tab\" data-lang=\"java\">Java</button>\n<button class=\"code-tab\" data-lang=\"python\">Python</button>\n<button class=\"code-tab\" data-lang=\"javascript\">JavaScript</button>\n<svg width=\"17\" class=\"copy-btn\" height=\"20\" viewBox=\"0 0 17 20\" fill=\"none\" xmlns=\"http://www.w3.org/2000/svg\">\n<path d=\"M2 20C1.45 20 0.979002 19.804 0.587002 19.412C0.195002 19.02 -0.000664969 18.5493 1.69779e-06 18V4H2V18H13V20H2ZM6 16C5.45 16 4.979 15.804 4.587 15.412C4.195 15.02 3.99934 14.5493 4 14V2C4 1.45 4.196 0.979002 4.588 0.587002C4.98 0.195002 5.45067 -0.000664969 6 1.69779e-06H15C15.55 1.69779e-06 16.021 0.196002 16.413 0.588002C16.805 0.980002 17.0007 1.45067 17 2V14C17 14.55 16.804 15.021 16.412 15.413C16.02 15.805 15.5493 16.0007 15 16H6ZM6 14H15V2H6V14Z\">\n</path>\n</svg>\n</div>\n<div class=\"code-content\">\n<div class=\"code-block dsa_article_code_active\" data-lang=\"cpp\">\n<pre class=\"wp-block-code\"><code lang=\"cpp\" class=\"language-cpp\">\n#include &lt;bits/stdc++.h&gt;\nusing namespace std;\n\nconst int mod = (int)1e9 + 7;\n\n// Function to count the number of ways to achieve the target sum\nint findWays(vector&lt;int&gt; &amp;num, int tar) {\n    int n = num.size();\n\n    vector&lt;int&gt; prev(tar + 1, 0);\n\n    if (num[0] == 0)\n        prev[0] = 2;  // 2 cases - pick and not pick\n    else\n        prev[0] = 1;  // 1 case - not pick\n\n    if (num[0] != 0 &amp;&amp; num[0] &lt;= tar)\n        prev[num[0]] = 1;  // 1 case - pick\n\n    for (int ind = 1; ind &lt; n; ind++) {\n        vector&lt;int&gt; cur(tar + 1, 0);\n        for (int target = 0; target &lt;= tar; target++) {\n            int notTaken = prev[target];\n\n            int taken = 0;\n            if (num[ind] &lt;= target)\n                taken = prev[target - num[ind]];\n\n            cur[target] = (notTaken + taken) % mod;\n        }\n        prev = cur;\n    }\n    return prev[tar];\n}\n\n// Function to calculate the number of ways to achieve the target sum\nint targetSum(int n, int target, vector&lt;int&gt;&amp; arr) {\n    int totSum = 0;\n    for (int i = 0; i &lt; n; i++) {\n        totSum += arr[i];\n    }\n\n    // Checking for edge cases\n    if (totSum - target &lt; 0 || (totSum - target) % 2 != 0)\n        return 0;  // Not possible to achieve the target sum\n\n    return findWays(arr, (totSum - target) / 2);\n}\n\nint main() {\n    vector&lt;int&gt; arr = {1, 2, 3, 1};\n    int n = arr.size();\n    int target = 3;\n\n    cout &lt;&lt; \"The number of subsets found is \" &lt;&lt; targetSum(n, target, arr) &lt;&lt; endl;\n\n    return 0;  // Return 0 to indicate successful program execution\n}\n</code>\n</pre>\n</div>\n<div class=\"code-block \" data-lang=\"java\">\n<pre class=\"wp-block-code\"><code lang=\"java\" class=\"language-java\">\nimport java.util.*;\n\nclass TUF {\n    static int mod = (int) (Math.pow(10, 9) + 7);\n\n    // Function to find the number of ways to achieve the target sum\n    static int findWays(int[] num, int tar) {\n        int n = num.length;\n\n        // Create an array to store results of subproblems for the current element\n        int prev[] = new int[tar + 1];\n\n        // Initialize the prev array for the first element of the array\n        if (num[0] == 0)\n            prev[0] = 2; // 2 cases - pick and not pick\n        else\n            prev[0] = 1; // 1 case - not pick\n\n        if (num[0] != 0 &amp;&amp; num[0] &lt;= tar)\n            prev[num[0]] = 1; // 1 case - pick\n\n        // Fill the prev array using dynamic programming\n        for (int ind = 1; ind &lt; n; ind++) {\n            int cur[] = new int[tar + 1];\n            for (int target = 0; target &lt;= tar; target++) {\n                int notTaken = prev[target];\n\n                int taken = 0;\n                if (num[ind] &lt;= target)\n                    taken = prev[target - num[ind]];\n\n                cur[target] = (notTaken + taken) % mod;\n            }\n            prev = cur;\n        }\n\n        return prev[tar];\n    }\n\n    // Function to calculate the number of ways to achieve the target sum\n    static int targetSum(int n, int target, int[] arr) {\n        int totSum = 0;\n\n        // Calculate the total sum of elements in the array\n        for (int i = 0; i &lt; n; i++) {\n            totSum += arr[i];\n        }\n\n        // Checking for edge cases\n        if (totSum - target &lt; 0 || (totSum - target) % 2 == 1)\n            return 0;\n\n        return findWays(arr, (totSum - target) / 2);\n    }\n\n    public static void main(String args[]) {\n        int arr[] = { 1, 2, 3, 1 };\n        int n = arr.length;\n        int target = 3;\n\n        // Call the targetSum function and print the result\n        System.out.println(\"The number of subsets found is \" + targetSum(n, target, arr));\n    }\n}\n</code>\n</pre>\n</div>\n<div class=\"code-block\" data-lang=\"python\">\n<pre class=\"wp-block-code\"><code lang=\"python\" class=\"language-python\">\nmod = int(1e9 + 7)\n\n# Function to find the number of ways to partition an array into two subsets\n# with a given target difference using dynamic programming\ndef findWays(num, tar):\n    n = len(num)\n\n    # Initialize a list 'prev' to store results for the previous element\n    prev = [0 for i in range(tar + 1)]\n\n    # Initialize 'prev' based on the first element of 'num'\n    if num[0] == 0:\n        prev[0] = 2  # Two cases - pick and not pick\n    else:\n        prev[0] = 1  # One case - not pick\n\n    if num[0] != 0 and num[0] &lt;= tar:\n        prev[num[0]] = 1  # One case - pick\n\n    for ind in range(1, n):\n        # Initialize a list 'cur' to store results for the current element\n        cur = [0 for i in range(tar + 1)]\n        for target in range(tar + 1):\n            notTaken = prev[target]\n\n            taken = 0\n            if num[ind] &lt;= target:\n                taken = prev[target - num[ind]]\n\n            # Store the result in 'cur' with modulo operation\n            cur[target] = (notTaken + taken) % mod\n        prev = cur\n\n    # Return the result for the target sum\n    return prev[tar]\n\n# Function to calculate the number of ways to achieve a target sum\ndef targetSum(n, target, arr):\n    totSum = 0\n    for i in range(n):\n        totSum += arr[i]\n\n    # Checking for edge cases\n    if (totSum - target) &lt; 0 or ((totSum - target) % 2):\n        return 0\n\n    # Calculate and return the number of ways using 'findWays' function\n    return findWays(arr, (totSum - target) // 2)\n\ndef main():\n    arr = [1, 2, 3, 1]\n    target = 3\n    n = len(arr)\n\n    # Print the number of ways found\n    print(\"The number of ways found is\", targetSum(n, target, arr))\n\nif __name__ == \"__main__\":\n    main()\n</code>\n</pre>\n</div>\n<div class=\"code-block\" data-lang=\"javascript\">\n<pre class=\"wp-block-code\"><code lang=\"javascript\" class=\"language-javascript\">\nconst mod = 1e9 + 7;\n\n// Define a function to find the number of ways to achieve the 'tar' target sum\nfunction findWays(num, tar) {\n    const n = num.length;\n\n    // Initialize an array 'prev' to store dynamic programming results, initialized with 0\n    let prev = new Array(tar + 1).fill(0);\n\n    if (num[0] === 0) prev[0] = 2;  // 2 cases - pick and not pick\n    else prev[0] = 1;  // 1 case - not pick\n\n    if (num[0] !== 0 &amp;&amp; num[0] &lt;= tar) prev[num[0]] = 1;  // 1 case - pick\n\n    for (let ind = 1; ind &lt; n; ind++) {\n        // Initialize an array 'cur' for the current iteration\n        let cur = new Array(tar + 1).fill(0);\n        for (let target = 0; target &lt;= tar; target++) {\n            const notTaken = prev[target];\n\n            let taken = 0;\n            if (num[ind] &lt;= target)\n                taken = prev[target - num[ind]];\n\n            cur[target] = (notTaken + taken) % mod;\n        }\n        // Update 'prev' to be the same as 'cur' for the next iteration\n        prev = [...cur];\n    }\n\n    return prev[tar];\n}\n\n// Define a function to find the number of ways to achieve the 'target' sum using elements from 'arr'\nfunction targetSum(n, target, arr) {\n    let totSum = 0;\n    for (let i = 0; i &lt; n; i++) {\n        totSum += arr[i];\n    }\n\n    // Checking for edge cases\n    if (totSum - target &lt; 0 || (totSum - target) % 2 !== 0) return 0;\n\n    // Calculate the second subset sum\n    const s2 = (totSum - target) / 2;\n\n    // Call the findWays function to calculate the result\n    return findWays(arr, s2);\n}\n\n// Main function\nfunction main() {\n    const arr = [1, 2, 3, 1];\n    const n = arr.length;\n    const target = 3;\n\n    // Call the targetSum function and print the result\n    console.log(\"The number of subsets found is \" + targetSum(n, target, arr));\n}\n\n// Call the main function to start the program\nmain();\n</code>\n</pre>\n</div>\n<p>\n<!-- Insert Output of Optimal Apporach Here -->\n<strong>Output:</strong>The number of ways found is 2\n\n\n</p>\n</div>\n</details>\n<details class=\"secondary-details\">\n<summary class=\"secondary-summary\">\n<span>\nComplexity Analysis\n</span>\n<svg class=\"arrow-svg opacity-75\" xmlns=\"http://www.w3.org/2000/svg\" viewBox=\"0 0 20 20\">\n<path d=\"M12.95 10.707l.707-.707L8 4.343 6.586 5.757 10.828 10l-4.242 4.243L8 15.657l4.95-4.95z\">\n</path>\n</svg>\n</summary>\n<p>\n\n<!-- Insert Time and Space Complexity of Optimal Approach-->\n</p><p><strong>Time Complexity: O(N*K)</strong></p>\n<p>Reason: There are three nested loops</p>\n<p><strong>Space Complexity: O(K)</strong></p>\n<p>Reason: We are using an external array of size \u2018K+1\u2019 to store only one row.</p>\n<p></p>\n</details>\n</div>\n</details>\n</div>\n<!-- Optimal Approach Starts from here -->\n</div>\n<!-- /wp:html -->\n\n<!-- wp:html -->\n<!-- This is Video Explination Drop-Down -->\n<div class=\"dsa_article_youtube_video\" id=\"dsa_article_video_explanation\">\n<details>\n<summary class=\"main-summary\">\n<span>\nVideo Explanation\n</span>\n<svg class=\"arrow-svg opacity-75\" xmlns=\"http://www.w3.org/2000/svg\" viewBox=\"0 0 20 20\">\n<path d=\"M12.95 10.707l.707-.707L8 4.343 6.586 5.757 10.828 10l-4.242 4.243L8 15.657l4.95-4.95z\"></path>\n</svg>\n</summary>\n<div class=\"yt-video-wrapper\">\n\n<!-- Insert iframe embed Link of Youtube Video-->\n<iframe class=\"lazy-loaded\" loading=\"lazy\" title=\"Target Sum\" width=\"810\" height=\"456\" data-lazy-type=\"iframe\" data-src=\"https://www.youtube.com/embed/b3GD8263-PQ?si=VDoMPPoC0OTtKWx2\" frameborder=\"0\" allow=\"accelerometer; autoplay; clipboard-write; encrypted-media; gyroscope; picture-in-picture; web-share\" allowfullscreen=\"\" src=\"https://www.youtube.com/embed/b3GD8263-PQ?feature=oembed\"></iframe><noscript>\n<iframe loading=\"lazy\" title=\"Target Sum\" width=\"810\" height=\"456\" src=\"https://www.youtube.com/embed/b3GD8263-PQ?si=VDoMPPoC0OTtKWx2\" frameborder=\"0\" allow=\"accelerometer; autoplay; clipboard-write; encrypted-media; gyroscope; picture-in-picture; web-share\" allowfullscreen=\"\"></iframe></noscript>\n</div>\n</details>\n</div>\n<!-- /wp:html -->\n\n<!-- wp:html -->\n<script>\n\nconst codeSections = document.querySelectorAll('.code-section');\n\n// Get last selected language from localStorage or set default value\nlet lastSelectedLanguage = localStorage.getItem('lastSelectedLanguage') || 'cpp'; \n\ncodeSections.forEach((section, sectionIndex) => {\nconst codeTabs = section.querySelectorAll('.code-tab');\nconst codeBlocks = section.querySelectorAll('.code-block');\nconst copyBtn = section.querySelector('.copy-btn');\n\ncodeTabs.forEach((tab) => {\ntab.addEventListener('click', () => {\ncodeTabs.forEach((t) => {\nt.classList.remove('dsa_article_code_active');\n});\ntab.classList.add('dsa_article_code_active');\n\nconst lang = tab.dataset.lang;\nconst activeBlock = section.querySelector(`.code-block[data-lang=\"${lang}\"]`);\ncodeBlocks.forEach((block) => {\nif (block === activeBlock) {\nblock.classList.add('dsa_article_code_active');\n} else {\nblock.classList.remove('dsa_article_code_active');\n}\n});\n\n// Update last selected language for all sections and store in localStorage\nlastSelectedLanguage = lang;\nlocalStorage.setItem('lastSelectedLanguage', lang);\ncodeSections.forEach((otherSection, otherIndex) => {\nif (otherIndex !== sectionIndex) {\nconst otherTabs = otherSection.querySelectorAll('.code-tab');\notherTabs.forEach((otherTab) => {\nif (otherTab.dataset.lang === lang) {\notherTab.classList.add('dsa_article_code_active');\n} else {\notherTab.classList.remove('dsa_article_code_active');\n}\n});\nconst otherActiveBlock = otherSection.querySelector(`.code-block[data-lang=\"${lang}\"]`);\nconst otherCodeBlocks = otherSection.querySelectorAll('.code-block');\notherCodeBlocks.forEach((block) => {\nif (block === otherActiveBlock) {\nblock.classList.add('dsa_article_code_active');\n} else {\nblock.classList.remove('dsa_article_code_active');\n}\n});\n}\n});\n});\n});\n\n// Handle copy button click event\ncopyBtn.addEventListener('click', () => {\nconst activeBlock = section.querySelector('.code-block.dsa_article_code_active code');\nnavigator.clipboard.writeText(activeBlock.innerText);\ncopyBtn.classList.add('dsa_article_code_active');\nsetTimeout(() => {\ncopyBtn.classList.remove('dsa_article_code_active');\n}, 1000);\n});\n});\n\n// Set initial state of the tabs\ncodeSections.forEach((section) => {\nconst codeTabs = section.querySelectorAll('.code-tab');\nconst codeBlocks = section.querySelectorAll('.code-block');\n\ncodeTabs.forEach((tab) => {\nif (tab.dataset.lang === lastSelectedLanguage) {\ntab.classList.add('dsa_article_code_active');\n} else {\ntab.classList.remove('dsa_article_code_active');\n}\n});\n\ncodeBlocks.forEach((block) => {\nif (block.dataset.lang === lastSelectedLanguage) {\nblock.classList.add('dsa_article_code_active');\n} else {\nblock.classList.remove('dsa_article_code_active');\n}\n});\n});\n</script>\n<script>\nconst codeSections = document.querySelectorAll('.code-section');\n\nlet lastSelectedLanguage = localStorage.getItem('lastSelectedLanguage') || 'cpp'; \n\ncodeSections.forEach((section, sectionIndex) => {\nconst codeTabs = section.querySelectorAll('.code-tab');\nconst codeBlocks = section.querySelectorAll('.code-block');\nconst copyBtn = section.querySelector('.copy-btn');\n\ncodeTabs.forEach((tab) => {\ntab.addEventListener('click', () => {\ncodeTabs.forEach((t) => {\nt.classList.remove('dsa_article_code_active');\n});\ntab.classList.add('dsa_article_code_active');\n\nconst lang = tab.dataset.lang;\nconst activeBlock = section.querySelector(`.code-block[data-lang=\"${lang}\"]`);\ncodeBlocks.forEach((block) => {\nif (block === activeBlock) {\nblock.classList.add('dsa_article_code_active');\n} else {\nblock.classList.remove('dsa_article_code_active');\n}\n});\n\nlastSelectedLanguage = lang;\nlocalStorage.setItem('lastSelectedLanguage', lang);\ncodeSections.forEach((otherSection, otherIndex) => {\nif (otherIndex !== sectionIndex) {\nconst otherTabs = otherSection.querySelectorAll('.code-tab');\notherTabs.forEach((otherTab) => {\nif (otherTab.dataset.lang === lang) {\notherTab.classList.add('dsa_article_code_active');\n} else {\notherTab.classList.remove('dsa_article_code_active');\n}\n});\nconst otherActiveBlock = otherSection.querySelector(`.code-block[data-lang=\"${lang}\"]`);\nconst otherCodeBlocks = otherSection.querySelectorAll('.code-block');\notherCodeBlocks.forEach((block) => {\nif (block === otherActiveBlock) {\nblock.classList.add('dsa_article_code_active');\n} else {\nblock.classList.remove('dsa_article_code_active');\n}\n});\n}\n});\n});\n});\n\ncopyBtn.addEventListener('click', () => {\nconst activeBlock = section.querySelector('.code-block.dsa_article_code_active code');\nnavigator.clipboard.writeText(activeBlock.innerText);\ncopyBtn.classList.add('dsa_article_code_active');\nsetTimeout(() => {\ncopyBtn.classList.remove('dsa_article_code_active');\n}, 1000);\n});\n});\n\ncodeSections.forEach((section) => {\nconst codeTabs = section.querySelectorAll('.code-tab');\nconst codeBlocks = section.querySelectorAll('.code-block');\n\ncodeTabs.forEach((tab) => {\nif (tab.dataset.lang === lastSelectedLanguage) {\ntab.classList.add('dsa_article_code_active');\n} else {\ntab.classList.remove('dsa_article_code_active');\n}\n});\n\ncodeBlocks.forEach((block) => {\nif (block.dataset.lang === lastSelectedLanguage) {\nblock.classList.add('dsa_article_code_active');\n} else {\nblock.classList.remove('dsa_article_code_active');\n}\n});\n});\n</script>\n<link rel=\"stylesheet\" href=\"https://cdnjs.cloudflare.com/ajax/libs/highlight.js/11.8.0/styles/atom-one-dark.min.css\">\n<script src=\"https://cdnjs.cloudflare.com/ajax/libs/highlight.js/11.8.0/highlight.min.js\"></script>\n<script src=\"https://cdnjs.cloudflare.com/ajax/libs/highlight.js/11.8.0/languages/go.min.js\"></script>\n<script src=\"index.js\"></script>\n<script>hljs.highlightAll();</script>\n<!-- /wp:html -->\n\n<!-- wp:html -->\n<script src=\"https://takeuforward.org/UXApproachDropDowns/3ApproachJSScript.js\"></script>\n<!-- /wp:html -->\n\n<!-- wp:quote -->\n<blockquote class=\"wp-block-quote\"><p><em>Special thanks to&nbsp;<strong><a href=\"https://www.linkedin.com/in/anshuman-sharma-a1b245194/\" target=\"_blank\" rel=\"noreferrer noopener\">Anshuman Sharma</a></strong>&nbsp;and <a href=\"https://www.linkedin.com/in/abhipsita-das-5b7069212/?originalSubdomain=in\" target=\"_blank\" rel=\"noopener\" title=\"\"><strong>Abhipsita Das</strong></a></em> <em>for contributing to this article on takeUforward. If you also wish to share your knowledge with the takeUforward fam,&nbsp;</em><a href=\"https://takeuforward.org/interviews/paid-work-from-home-internship-at-takeuforward/\">please check out this article</a></p></blockquote>\n<!-- /wp:quote -->",
    "category_tag": "data-structure",
    "likes": 48,
    "preview": "Problem Link: Target Sum Problem Description: We are given an array \u2018ARR\u2019 of size \u2018N\u2019 and a number \u2018Target\u2019. Our task is to build an expression from the given array where we can place a \u2018+\u2019 or \u2018-\u2019..."
}